twiskey.py
twiskey-0.1.0.dist-info/WHEEL
twiskey-0.1.0.dist-info/METADATA
twiskey-0.1.0.dist-info/RECORD
